[{"id": 1,
  "name": "Akolita",
  "baseProfession": true,
  "exitChance": 0.4,
  "statistics": null,
  "skills": null,
  "talents": null,
  "careerExits": null,
  "dominatingStat": "",
  "properties": "",
  "bestNextCareer": ""},
  {"id": 2,
    "name": "Banita",
    "baseProfession": true,
    "exitChance": 0.4,
    "statistics": null,
    "skills": null,
    "talents": null,
    "careerExits": null,
    "dominatingStat": "",
    "properties": "",
    "bestNextCareer": ""},
  {"id": 3,
    "name": "Berserker z Norski",
    "baseProfession": true,
    "exitChance": 0.4,
    "statistics": null,
    "skills": null,
    "talents": null,
    "careerExits": null,
    "dominatingStat": "",
    "properties": "",
    "bestNextCareer": ""},
  {"id": 4,
    "name": "Chłop",
    "baseProfession": true,
    "exitChance": 0.4,
    "statistics": null,
    "skills": null,
    "talents": null,
    "careerExits": null,
    "dominatingStat": "",
    "properties": "",
    "bestNextCareer": ""},
  {"id": 5,
    "name": "Ciura obozowa",
    "baseProfession": true,
    "exitChance": 0.4,
    "statistics": null,
    "skills": null,
    "talents": null,
    "careerExits": null,
    "dominatingStat": "",
    "properties": "",
    "bestNextCareer": ""},
  {"id": 6,
    "name": "Cyrkowiec",
    "baseProfession": true,
    "exitChance": 0.4,
    "statistics": null,
    "skills": null,
    "talents": null,
    "careerExits": null,
    "dominatingStat": "",
    "properties": "",
    "bestNextCareer": ""},
  {"id": 7,
    "name": "Cyrulik",
    "baseProfession": true,
    "exitChance": 0.4,
    "statistics": null,
    "skills": null,
    "talents": null,
    "careerExits": null,
    "dominatingStat": "",
    "properties": "",
    "bestNextCareer": ""},
  {"id": 8,
    "name": "Fanatyk",
    "baseProfession": true,
    "exitChance": 0.4,
    "statistics": null,
    "skills": null,
    "talents": null,
    "careerExits": null,
    "dominatingStat": "",
    "properties": "",
    "bestNextCareer": ""},
  {"id": 9,
    "name": "Flisak",
    "baseProfession": true,
    "exitChance": 0.4,
    "statistics": null,
    "skills": null,
    "talents": null,
    "careerExits": null,
    "dominatingStat": "",
    "properties": "",
    "bestNextCareer": ""},
  {"id": 10,
    "name": "Giermek",
    "baseProfession": true,
    "exitChance": 0.4,
    "statistics": null,
    "skills": null,
    "talents": null,
    "careerExits": null,
    "dominatingStat": "",
    "properties": "",
    "bestNextCareer": ""},
  {"id": 11,
    "name": "Gladiator",
    "baseProfession": true,
    "exitChance": 0.4,
    "statistics": null,
    "skills": null,
    "talents": null,
    "careerExits": null,
    "dominatingStat": "",
    "properties": "",
    "bestNextCareer": ""},
  {"id": 12,
    "name": "Goniec",
    "baseProfession": true,
    "exitChance": 0.4,
    "statistics": null,
    "skills": null,
    "talents": null,
    "careerExits": null,
    "dominatingStat": "",
    "properties": "",
    "bestNextCareer": ""},
  {"id": 13,
    "name": "Górnik",
    "baseProfession": true,
    "exitChance": 0.4,
    "statistics": null,
    "skills": null,
    "talents": null,
    "careerExits": null,
    "dominatingStat": "",
    "properties": "",
    "bestNextCareer": ""},
  {"id": 14,
    "name": "Guślarz",
    "baseProfession": true,
    "exitChance": 0.4,
    "statistics": null,
    "skills": null,
    "talents": null,
    "careerExits": null,
    "dominatingStat": "",
    "properties": "",
    "bestNextCareer": ""},
  {"id": 15,
    "name": "Hiena cmentarna",
    "baseProfession": true,
    "exitChance": 0.4,
    "statistics": null,
    "skills": null,
    "talents": null,
    "careerExits": null,
    "dominatingStat": "",
    "properties": "",
    "bestNextCareer": ""},
  {"id": 16,
    "name": "Kanciarz",
    "baseProfession": true,
    "exitChance": 0.4,
    "statistics": null,
    "skills": null,
    "talents": null,
    "careerExits": null,
    "dominatingStat": "",
    "properties": "",
    "bestNextCareer": ""},
  {"id": 17,
    "name": "Kozak kislevski",
    "baseProfession": true,
    "exitChance": 0.4,
    "statistics": null,
    "skills": null,
    "talents": null,
    "careerExits": null,
    "dominatingStat": "",
    "properties": "",
    "bestNextCareer": ""},
  {"id": 18,
    "name": "Leśnik",
    "baseProfession": true,
    "exitChance": 0.4,
    "statistics": null,
    "skills": null,
    "talents": null,
    "careerExits": null,
    "dominatingStat": "",
    "properties": "",
    "bestNextCareer": ""},
  {"id": 19,
    "name": "Łowca",
    "baseProfession": true,
    "exitChance": 0.4,
    "statistics": null,
    "skills": null,
    "talents": null,
    "careerExits": null,
    "dominatingStat": "",
    "properties": "",
    "bestNextCareer": ""},
  {"id": 20,
    "name": "Łowca nagród",
    "baseProfession": true,
    "exitChance": 0.4,
    "statistics": null,
    "skills": null,
    "talents": null,
    "careerExits": null,
    "dominatingStat": "",
    "properties": "",
    "bestNextCareer": ""},
  {"id": 21,
    "name": "Mieszczanin",
    "baseProfession": true,
    "exitChance": 0.4,
    "statistics": null,
    "skills": null,
    "talents": null,
    "careerExits": null,
    "dominatingStat": "",
    "properties": "",
    "bestNextCareer": ""},
  {"id": 22,
    "name": "Mytnik",
    "baseProfession": true,
    "exitChance": 0.4,
    "statistics": null,
    "skills": null,
    "talents": null,
    "careerExits": null,
    "dominatingStat": "",
    "properties": "",
    "bestNextCareer": ""},
  {"id": 23,
    "name": "Najemnik",
    "baseProfession": true,
    "exitChance": 0.4,
    "statistics": null,
    "skills": null,
    "talents": null,
    "careerExits": null,
    "dominatingStat": "",
    "properties": "",
    "bestNextCareer": ""},
  {"id": 24,
    "name": "Ochotnik",
    "baseProfession": true,
    "exitChance": 0.4,
    "statistics": null,
    "skills": null,
    "talents": null,
    "careerExits": null,
    "dominatingStat": "",
    "properties": "",
    "bestNextCareer": ""},
  {"id": 25,
    "name": "Ochroniarz",
    "baseProfession": true,
    "exitChance": 0.4,
    "statistics": null,
    "skills": null,
    "talents": null,
    "careerExits": null,
    "dominatingStat": "",
    "properties": "",
    "bestNextCareer": ""},
  {"id": 26,
    "name": "Oprych",
    "baseProfession": true,
    "exitChance": 0.4,
    "statistics": null,
    "skills": null,
    "talents": null,
    "careerExits": null,
    "dominatingStat": "",
    "properties": "",
    "bestNextCareer": ""},
  {"id": 27,
    "name": "Paź",
    "baseProfession": true,
    "exitChance": 0.4,
    "statistics": null,
    "skills": null,
    "talents": null,
    "careerExits": null,
    "dominatingStat": "",
    "properties": "",
    "bestNextCareer": ""},
  {"id": 28,
    "name": "Podżegacz",
    "baseProfession": true,
    "exitChance": 0.4,
    "statistics": null,
    "skills": null,
    "talents": null,
    "careerExits": null,
    "dominatingStat": "",
    "properties": "",
    "bestNextCareer": ""},
  {"id": 29,
    "name": "Porywacz zwłok",
    "baseProfession": true,
    "exitChance": 0.4,
    "statistics": null,
    "skills": null,
    "talents": null,
    "careerExits": null,
    "dominatingStat": "",
    "properties": "",
    "bestNextCareer": ""},
  {"id": 30,
    "name": "Posłaniec",
    "baseProfession": true,
    "exitChance": 0.4,
    "statistics": null,
    "skills": null,
    "talents": null,
    "careerExits": null,
    "dominatingStat": "",
    "properties": "",
    "bestNextCareer": ""},
  {"id": 31,
    "name": "Przemytnik",
    "baseProfession": true,
    "exitChance": 0.4,
    "statistics": null,
    "skills": null,
    "talents": null,
    "careerExits": null,
    "dominatingStat": "",
    "properties": "",
    "bestNextCareer": ""},
  {"id": 32,
    "name": "Przepatrywacz",
    "baseProfession": true,
    "exitChance": 0.4,
    "statistics": null,
    "skills": null,
    "talents": null,
    "careerExits": null,
    "dominatingStat": "",
    "properties": "",
    "bestNextCareer": ""},
  {"id": 33,
    "name": "Przewoźnik",
    "baseProfession": true,
    "exitChance": 0.4,
    "statistics": null,
    "skills": null,
    "talents": null,
    "careerExits": null,
    "dominatingStat": "",
    "properties": "",
    "bestNextCareer": ""},
  {"id": 34,
    "name": "Rybak",
    "baseProfession": true,
    "exitChance": 0.4,
    "statistics": null,
    "skills": null,
    "talents": null,
    "careerExits": null,
    "dominatingStat": "",
    "properties": "",
    "bestNextCareer": ""},
  {"id": 35,
    "name": "Rzecznik rodu",
    "baseProfession": true,
    "exitChance": 0.4,
    "statistics": null,
    "skills": null,
    "talents": null,
    "careerExits": null,
    "dominatingStat": "",
    "properties": "",
    "bestNextCareer": ""},
  {"id": 36,
    "name": "Rzemieślnik",
    "baseProfession": true,
    "exitChance": 0.4,
    "statistics": null,
    "skills": null,
    "talents": null,
    "careerExits": null,
    "dominatingStat": "",
    "properties": "",
    "bestNextCareer": ""},
  {"id": 37,
    "name": "Rzezimieszek",
    "baseProfession": true,
    "exitChance": 0.4,
    "statistics": null,
    "skills": null,
    "talents": null,
    "careerExits": null,
    "dominatingStat": "",
    "properties": "",
    "bestNextCareer": ""},
  {"id": 38,
    "name": "Skryba",
    "baseProfession": true,
    "exitChance": 0.4,
    "statistics": null,
    "skills": null,
    "talents": null,
    "careerExits": null,
    "dominatingStat": "",
    "properties": "",
    "bestNextCareer": ""},
  {"id": 39,
    "name": "Sługa",
    "baseProfession": true,
    "exitChance": 0.4,
    "statistics": null,
    "skills": null,
    "talents": null,
    "careerExits": null,
    "dominatingStat": "",
    "properties": "",
    "bestNextCareer": ""},
  {"id": 40,
    "name": "Strażnik",
    "baseProfession": true,
    "exitChance": 0.4,
    "statistics": null,
    "skills": null,
    "talents": null,
    "careerExits": null,
    "dominatingStat": "",
    "properties": "",
    "bestNextCareer": ""},
  {"id": 41,
    "name": "Strażnik dróg",
    "baseProfession": true,
    "exitChance": 0.4,
    "statistics": null,
    "skills": null,
    "talents": null,
    "careerExits": null,
    "dominatingStat": "",
    "properties": "",
    "bestNextCareer": ""},
  {"id": 42,
    "name": "Strażnik pól",
    "baseProfession": true,
    "exitChance": 0.4,
    "statistics": null,
    "skills": null,
    "talents": null,
    "careerExits": null,
    "dominatingStat": "",
    "properties": "",
    "bestNextCareer": ""},
  {"id": 43,
    "name": "Strażnik więzienny",
    "baseProfession": true,
    "exitChance": 0.4,
    "statistics": null,
    "skills": null,
    "talents": null,
    "careerExits": null,
    "dominatingStat": "",
    "properties": "",
    "bestNextCareer": ""},
  {"id": 44,
    "name": "Szczurołap",
    "baseProfession": true,
    "exitChance": 0.4,
    "statistics": null,
    "skills": null,
    "talents": null,
    "careerExits": null,
    "dominatingStat": "",
    "properties": "",
    "bestNextCareer": ""},
  {"id": 45,
    "name": "Szermierz estalijski",
    "baseProfession": true,
    "exitChance": 0.4,
    "statistics": null,
    "skills": null,
    "talents": null,
    "careerExits": null,
    "dominatingStat": "",
    "properties": "",
    "bestNextCareer": ""},
  {"id": 46,
    "name": "Szlachcic",
    "baseProfession": true,
    "exitChance": 0.4,
    "statistics": null,
    "skills": null,
    "talents": null,
    "careerExits": null,
    "dominatingStat": "",
    "properties": "",
    "bestNextCareer": ""},
  {"id": 47,
    "name": "Śmieciarz",
    "baseProfession": true,
    "exitChance": 0.4,
    "statistics": null,
    "skills": null,
    "talents": null,
    "careerExits": null,
    "dominatingStat": "",
    "properties": "",
    "bestNextCareer": ""},
  {"id": 48,
    "name": "Tarczownik",
    "baseProfession": true,
    "exitChance": 0.4,
    "statistics": null,
    "skills": null,
    "talents": null,
    "careerExits": null,
    "dominatingStat": "",
    "properties": "",
    "bestNextCareer": ""},
  {"id": 49,
    "name": "Uczeń czarodzieja",
    "baseProfession": true,
    "exitChance": 0.4,
    "statistics": null,
    "skills": null,
    "talents": null,
    "careerExits": null,
    "dominatingStat": "",
    "properties": "",
    "bestNextCareer": ""},
  {"id": 50,
    "name": "Węglarz",
    "baseProfession": true,
    "exitChance": 0.4,
    "statistics": null,
    "skills": null,
    "talents": null,
    "careerExits": null,
    "dominatingStat": "",
    "properties": "",
    "bestNextCareer": ""},
  {"id": 51,
    "name": "Włóczykij",
    "baseProfession": true,
    "exitChance": 0.4,
    "statistics": null,
    "skills": null,
    "talents": null,
    "careerExits": null,
    "dominatingStat": "",
    "properties": "",
    "bestNextCareer": ""},
  {"id": 52,
    "name": "Wojownik klanowy",
    "baseProfession": true,
    "exitChance": 0.4,
    "statistics": null,
    "skills": null,
    "talents": null,
    "careerExits": null,
    "dominatingStat": "",
    "properties": "",
    "bestNextCareer": ""},
  {"id": 53,
    "name": "Woźnica",
    "baseProfession": true,
    "exitChance": 0.4,
    "statistics": null,
    "skills": null,
    "talents": null,
    "careerExits": null,
    "dominatingStat": "",
    "properties": "",
    "bestNextCareer": ""},
  {"id": 54,
    "name": "Zabójca trolli",
    "baseProfession": true,
    "exitChance": 0.4,
    "statistics": null,
    "skills": null,
    "talents": null,
    "careerExits": null,
    "dominatingStat": "",
    "properties": "",
    "bestNextCareer": ""},
  {"id": 55,
    "name": "Zarządca",
    "baseProfession": true,
    "exitChance": 0.4,
    "statistics": null,
    "skills": null,
    "talents": null,
    "careerExits": null,
    "dominatingStat": "",
    "properties": "",
    "bestNextCareer": ""},
  {"id": 56,
    "name": "Złodziej",
    "baseProfession": true,
    "exitChance": 0.4,
    "statistics": null,
    "skills": null,
    "talents": null,
    "careerExits": null,
    "dominatingStat": "",
    "properties": "",
    "bestNextCareer": ""},
  {"id": 57,
    "name": "Żak",
    "baseProfession": true,
    "exitChance": 0.4,
    "statistics": null,
    "skills": null,
    "talents": null,
    "careerExits": null,
    "dominatingStat": "",
    "properties": "",
    "bestNextCareer": ""},
  {"id": 58,
    "name": "Żeglarz",
    "baseProfession": true,
    "exitChance": 0.4,
    "statistics": null,
    "skills": null,
    "talents": null,
    "careerExits": null,
    "dominatingStat": "",
    "properties": "",
    "bestNextCareer": ""},
  {"id": 59,
    "name": "Żołnierz",
    "baseProfession": true,
    "exitChance": 0.4,
    "statistics": null,
    "skills": null,
    "talents": null,
    "careerExits": null,
    "dominatingStat": "",
    "properties": "",
    "bestNextCareer": ""},
  {"id": 60,
    "name": "Żołnierz okrętowy",
    "baseProfession": true,
    "exitChance": 0.4,
    "statistics": null,
    "skills": null,
    "talents": null,
    "careerExits": null,
    "dominatingStat": "",
    "properties": "",
    "bestNextCareer": ""},
  {"id": 61,
    "name": "Arcykapłan",
    "baseProfession": false,
    "exitChance": 0.4,
    "statistics": null,
    "skills": null,
    "talents": null,
    "careerExits": null,
    "dominatingStat": "",
    "properties": "",
    "bestNextCareer": ""},
  {"id": 62,
    "name": "Arcymag",
    "baseProfession": false,
    "exitChance": 0.4,
    "statistics": null,
    "skills": null,
    "talents": null,
    "careerExits": null,
    "dominatingStat": "",
    "properties": "",
    "bestNextCareer": ""},
  {"id": 63,
    "name": "Arystokrata",
    "baseProfession": false,
    "exitChance": 0.4,
    "statistics": null,
    "skills": null,
    "talents": null,
    "careerExits": null,
    "dominatingStat": "",
    "properties": "",
    "bestNextCareer": ""},
  {"id": 64,
    "name": "Bard",
    "baseProfession": false,
    "exitChance": 0.4,
    "statistics": null,
    "skills": null,
    "talents": null,
    "careerExits": null,
    "dominatingStat": "",
    "properties": "",
    "bestNextCareer": ""},
  {"id": 65,
    "name": "Biczownik",
    "baseProfession": false,
    "exitChance": 0.4,
    "statistics": null,
    "skills": null,
    "talents": null,
    "careerExits": null,
    "dominatingStat": "",
    "properties": "",
    "bestNextCareer": ""},
  {"id": 66,
    "name": "Bosman",
    "baseProfession": false,
    "exitChance": 0.4,
    "statistics": null,
    "skills": null,
    "talents": null,
    "careerExits": null,
    "dominatingStat": "",
    "properties": "",
    "bestNextCareer": ""},
  {"id": 67,
    "name": "Demagog",
    "baseProfession": false,
    "exitChance": 0.4,
    "statistics": null,
    "skills": null,
    "talents": null,
    "careerExits": null,
    "dominatingStat": "",
    "properties": "",
    "bestNextCareer": ""},
  {"id": 68,
    "name": "Dworzanin",
    "baseProfession": false,
    "exitChance": 0.4,
    "statistics": null,
    "skills": null,
    "talents": null,
    "careerExits": null,
    "dominatingStat": "",
    "properties": "",
    "bestNextCareer": ""},
  {"id": 69,
    "name": "Fechtmistrz",
    "baseProfession": false,
    "exitChance": 0.4,
    "statistics": null,
    "skills": null,
    "talents": null,
    "careerExits": null,
    "dominatingStat": "",
    "properties": "",
    "bestNextCareer": ""},
  {"id": 70,
    "name": "Herold",
    "baseProfession": false,
    "exitChance": 0.4,
    "statistics": null,
    "skills": null,
    "talents": null,
    "careerExits": null,
    "dominatingStat": "",
    "properties": "",
    "bestNextCareer": ""},
  {"id": 71,
    "name": "Herszt banitów",
    "baseProfession": false,
    "exitChance": 0.4,
    "statistics": null,
    "skills": null,
    "talents": null,
    "careerExits": null,
    "dominatingStat": "",
    "properties": "",
    "bestNextCareer": ""},
  {"id": 72,
    "name": "Inżynier",
    "baseProfession": false,
    "exitChance": 0.4,
    "statistics": null,
    "skills": null,
    "talents": null,
    "careerExits": null,
    "dominatingStat": "",
    "properties": "",
    "bestNextCareer": ""},
  {"id": 73,
    "name": "Kapitan",
    "baseProfession": false,
    "exitChance": 0.4,
    "statistics": null,
    "skills": null,
    "talents": null,
    "careerExits": null,
    "dominatingStat": "",
    "properties": "",
    "bestNextCareer": ""},
  {"id": 74,
    "name": "Kapłan",
    "baseProfession": false,
    "exitChance": 0.4,
    "statistics": null,
    "skills": null,
    "talents": null,
    "careerExits": null,
    "dominatingStat": "",
    "properties": "",
    "bestNextCareer": ""},
  {"id": 75,
    "name": "Karczmarz",
    "baseProfession": false,
    "exitChance": 0.4,
    "statistics": null,
    "skills": null,
    "talents": null,
    "careerExits": null,
    "dominatingStat": "",
    "properties": "",
    "bestNextCareer": ""},
  {"id": 76,
    "name": "Książę złodziei",
    "baseProfession": false,
    "exitChance": 0.4,
    "statistics": null,
    "skills": null,
    "talents": null,
    "careerExits": null,
    "dominatingStat": "",
    "properties": "",
    "bestNextCareer": ""},
  {"id": 77,
    "name": "Kupiec",
    "baseProfession": false,
    "exitChance": 0.4,
    "statistics": null,
    "skills": null,
    "talents": null,
    "careerExits": null,
    "dominatingStat": "",
    "properties": "",
    "bestNextCareer": ""},
  {"id": 78,
    "name": "Leśny duch",
    "baseProfession": false,
    "exitChance": 0.4,
    "statistics": null,
    "skills": null,
    "talents": null,
    "careerExits": null,
    "dominatingStat": "",
    "properties": "",
    "bestNextCareer": ""},
  {"id": 79,
    "name": "Łowca czarownic",
    "baseProfession": false,
    "exitChance": 0.4,
    "statistics": null,
    "skills": null,
    "talents": null,
    "careerExits": null,
    "dominatingStat": "",
    "properties": "",
    "bestNextCareer": ""},
  {"id": 80,
    "name": "Łowca wampirów",
    "baseProfession": false,
    "exitChance": 0.4,
    "statistics": null,
    "skills": null,
    "talents": null,
    "careerExits": null,
    "dominatingStat": "",
    "properties": "",
    "bestNextCareer": ""},
  {"id": 81,
    "name": "Majordomus",
    "baseProfession": false,
    "exitChance": 0.4,
    "statistics": null,
    "skills": null,
    "talents": null,
    "careerExits": null,
    "dominatingStat": "",
    "properties": "",
    "bestNextCareer": ""},
  {"id": 82,
    "name": "Medyk",
    "baseProfession": false,
    "exitChance": 0.4,
    "statistics": null,
    "skills": null,
    "talents": null,
    "careerExits": null,
    "dominatingStat": "",
    "properties": "",
    "bestNextCareer": ""},
  {"id": 83,
    "name": "Mistrz cieni",
    "baseProfession": false,
    "exitChance": 0.4,
    "statistics": null,
    "skills": null,
    "talents": null,
    "careerExits": null,
    "dominatingStat": "",
    "properties": "",
    "bestNextCareer": ""},
  {"id": 84,
    "name": "Mistrz gildii",
    "baseProfession": false,
    "exitChance": 0.4,
    "statistics": null,
    "skills": null,
    "talents": null,
    "careerExits": null,
    "dominatingStat": "",
    "properties": "",
    "bestNextCareer": ""},
  {"id": 85,
    "name": "Mistrz magii",
    "baseProfession": false,
    "exitChance": 0.4,
    "statistics": null,
    "skills": null,
    "talents": null,
    "careerExits": null,
    "dominatingStat": "",
    "properties": "",
    "bestNextCareer": ""},
  {"id": 86,
    "name": "Mistrz rzemiosła",
    "baseProfession": false,
    "exitChance": 0.4,
    "statistics": null,
    "skills": null,
    "talents": null,
    "careerExits": null,
    "dominatingStat": "",
    "properties": "",
    "bestNextCareer": ""},
  {"id": 87,
    "name": "Mistrz zakonny",
    "baseProfession": false,
    "exitChance": 0.4,
    "statistics": null,
    "skills": null,
    "talents": null,
    "careerExits": null,
    "dominatingStat": "",
    "properties": "",
    "bestNextCareer": ""},
  {"id": 88,
    "name": "Nawigator",
    "baseProfession": false,
    "exitChance": 0.4,
    "statistics": null,
    "skills": null,
    "talents": null,
    "careerExits": null,
    "dominatingStat": "",
    "properties": "",
    "bestNextCareer": ""},
  {"id": 89,
    "name": "Odkrywca",
    "baseProfession": false,
    "exitChance": 0.4,
    "statistics": null,
    "skills": null,
    "talents": null,
    "careerExits": null,
    "dominatingStat": "",
    "properties": "",
    "bestNextCareer": ""},
  {"id": 90,
    "name": "Oficer",
    "baseProfession": false,
    "exitChance": 0.4,
    "statistics": null,
    "skills": null,
    "talents": null,
    "careerExits": null,
    "dominatingStat": "",
    "properties": "",
    "bestNextCareer": ""},
  {"id": 91,
    "name": "Oprawca",
    "baseProfession": false,
    "exitChance": 0.4,
    "statistics": null,
    "skills": null,
    "talents": null,
    "careerExits": null,
    "dominatingStat": "",
    "properties": "",
    "bestNextCareer": ""},
  {"id": 92,
    "name": "Paser",
    "baseProfession": false,
    "exitChance": 0.4,
    "statistics": null,
    "skills": null,
    "talents": null,
    "careerExits": null,
    "dominatingStat": "",
    "properties": "",
    "bestNextCareer": ""},
  {"id": 93,
    "name": "Rajtar",
    "baseProfession": false,
    "exitChance": 0.4,
    "statistics": null,
    "skills": null,
    "talents": null,
    "careerExits": null,
    "dominatingStat": "",
    "properties": "",
    "bestNextCareer": ""},
  {"id": 94,
    "name": "Reketer",
    "baseProfession": false,
    "exitChance": 0.4,
    "statistics": null,
    "skills": null,
    "talents": null,
    "careerExits": null,
    "dominatingStat": "",
    "properties": "",
    "bestNextCareer": ""},
  {"id": 95,
    "name": "Rozbójnik",
    "baseProfession": false,
    "exitChance": 0.4,
    "statistics": null,
    "skills": null,
    "talents": null,
    "careerExits": null,
    "dominatingStat": "",
    "properties": "",
    "bestNextCareer": ""},
  {"id": 96,
    "name": "Rycerz",
    "baseProfession": false,
    "exitChance": 0.4,
    "statistics": null,
    "skills": null,
    "talents": null,
    "careerExits": null,
    "dominatingStat": "",
    "properties": "",
    "bestNextCareer": ""},
  {"id": 97,
    "name": "Sierżant",
    "baseProfession": false,
    "exitChance": 0.4,
    "statistics": null,
    "skills": null,
    "talents": null,
    "careerExits": null,
    "dominatingStat": "",
    "properties": "",
    "bestNextCareer": ""},
  {"id": 98,
    "name": "Skrytobójca",
    "baseProfession": false,
    "exitChance": 0.4,
    "statistics": null,
    "skills": null,
    "talents": null,
    "careerExits": null,
    "dominatingStat": "",
    "properties": "",
    "bestNextCareer": ""},
  {"id": 99,
    "name": "Strzelec",
    "baseProfession": false,
    "exitChance": 0.4,
    "statistics": null,
    "skills": null,
    "talents": null,
    "careerExits": null,
    "dominatingStat": "",
    "properties": "",
    "bestNextCareer": ""},
  {"id": 100,
    "name": "Szampierz",
    "baseProfession": false,
    "exitChance": 0.4,
    "statistics": null,
    "skills": null,
    "talents": null,
    "careerExits": null,
    "dominatingStat": "",
    "properties": "",
    "bestNextCareer": ""},
  {"id": 101,
    "name": "Szarlatan",
    "baseProfession": false,
    "exitChance": 0.4,
    "statistics": null,
    "skills": null,
    "talents": null,
    "careerExits": null,
    "dominatingStat": "",
    "properties": "",
    "bestNextCareer": ""},
  {"id": 102,
    "name": "Szpieg",
    "baseProfession": false,
    "exitChance": 0.4,
    "statistics": null,
    "skills": null,
    "talents": null,
    "careerExits": null,
    "dominatingStat": "",
    "properties": "",
    "bestNextCareer": ""},
  {"id": 103,
    "name": "Uczony",
    "baseProfession": false,
    "exitChance": 0.4,
    "statistics": null,
    "skills": null,
    "talents": null,
    "careerExits": null,
    "dominatingStat": "",
    "properties": "",
    "bestNextCareer": ""},
  {"id": 104,
    "name": "Urzędnik",
    "baseProfession": false,
    "exitChance": 0.4,
    "statistics": null,
    "skills": null,
    "talents": null,
    "careerExits": null,
    "dominatingStat": "",
    "properties": "",
    "bestNextCareer": ""},
  {"id": 105,
    "name": "Weteran",
    "baseProfession": false,
    "exitChance": 0.4,
    "statistics": null,
    "skills": null,
    "talents": null,
    "careerExits": null,
    "dominatingStat": "",
    "properties": "",
    "bestNextCareer": ""},
  {"id": 106,
    "name": "Wędrowny czarodziej",
    "baseProfession": false,
    "exitChance": 0.4,
    "statistics": null,
    "skills": null,
    "talents": null,
    "careerExits": null,
    "dominatingStat": "",
    "properties": "",
    "bestNextCareer": ""},
  {"id": 107,
    "name": "Włamywacz",
    "baseProfession": false,
    "exitChance": 0.4,
    "statistics": null,
    "skills": null,
    "talents": null,
    "careerExits": null,
    "dominatingStat": "",
    "properties": "",
    "bestNextCareer": ""},
  {"id": 108,
    "name": "Wybraniec boży",
    "baseProfession": false,
    "exitChance": 0.4,
    "statistics": null,
    "skills": null,
    "talents": null,
    "careerExits": null,
    "dominatingStat": "",
    "properties": "",
    "bestNextCareer": ""},
  {"id": 109,
    "name": "Zabójca demonów",
    "baseProfession": false,
    "exitChance": 0.4,
    "statistics": null,
    "skills": null,
    "talents": null,
    "careerExits": null,
    "dominatingStat": "",
    "properties": "",
    "bestNextCareer": ""},
  {"id": 110,
    "name": "Zabójca olbrzymów",
    "baseProfession": false,
    "exitChance": 0.4,
    "statistics": null,
    "skills": null,
    "talents": null,
    "careerExits": null,
    "dominatingStat": "",
    "properties": "",
    "bestNextCareer": ""},
  {"id": 111,
    "name": "Zakonnik",
    "baseProfession": false,
    "exitChance": 0.4,
    "statistics": null,
    "skills": null,
    "talents": null,
    "careerExits": null,
    "dominatingStat": "",
    "properties": "",
    "bestNextCareer": ""},
  {"id": 112,
    "name": "Zwadźca",
    "baseProfession": false,
    "exitChance": 0.4,
    "statistics": null,
    "skills": null,
    "talents": null,
    "careerExits": null,
    "dominatingStat": "",
    "properties": "",
    "bestNextCareer": ""},
  {"id": 113,
    "name": "Zwiadowca",
    "baseProfession": false,
    "exitChance": 0.4,
    "statistics": null,
    "skills": null,
    "talents": null,
    "careerExits": null,
    "dominatingStat": "",
    "properties": "",
    "bestNextCareer": ""}
]